memfuse/__init__.py
memfuse/api/__init__.py
memfuse/api/agents.py
memfuse/api/api_keys.py
memfuse/api/base.py
memfuse/api/health.py
memfuse/api/knowledge.py
memfuse/api/memory.py
memfuse/api/messages.py
memfuse/api/sessions.py
memfuse/api/users.py
memfuse/client.py
memfuse/llm/__init__.py
memfuse/llm/anthropic_adapter.py
memfuse/llm/gemini_adapter.py
memfuse/llm/ollama_adapter.py
memfuse/llm/openai_adapter.py
memfuse/memory.py
memfuse/models/__init__.py
memfuse/models/requests.py
memfuse/models/responses.py
memfuse/prompts/__init__.py
memfuse/prompts/prompt_context.py
memfuse/prompts/prompt_formatter.py
memfuse/prompts/prompt_manager.py
memfuse/prompts/templates/distractor_system.j2
memfuse/prompts/templates/distractor_user.j2
memfuse/prompts/templates/question_answering_system.j2
memfuse/prompts/templates/question_answering_user.j2
memfuse/utils/__init__.py
memfuse/utils/error_handling.py
memfuse/utils/version_compatibility.py
memfuse-0.3.3.dist-info/METADATA
memfuse-0.3.3.dist-info/WHEEL
memfuse-0.3.3.dist-info/licenses/LICENSE
memfuse-0.3.3.dist-info/RECORD
