Metadata-Version: 2.4
Name: memfuse
Version: 0.3.3
Summary: Memfuse Python SDK
License: Apache-2.0
License-File: LICENSE
Keywords: memfuse,sdk,ai,llm,memory,rag
Author: Calvin Ku
Author-email: cku@percena.co
Requires-Python: >=3.10,<4.0
Classifier: Development Status :: 3 - Alpha
Classifier: Intended Audience :: Developers
Classifier: License :: OSI Approved :: Apache Software License
Classifier: Operating System :: OS Independent
Classifier: Programming Language :: Python :: 3
Classifier: Programming Language :: Python :: 3.10
Classifier: Programming Language :: Python :: 3.11
Classifier: Programming Language :: Python :: 3.12
Classifier: Programming Language :: Python :: 3.13
Classifier: Programming Language :: Python :: 3.14
Classifier: Topic :: Software Development :: Libraries :: Python Modules
Provides-Extra: full
Provides-Extra: ui
Requires-Dist: aiohttp[speedups] (>=3.11.18,<4.0.0)
Requires-Dist: anthropic (>=0.51.0,<0.52.0)
Requires-Dist: google-genai (>=1.16.1,<2.0.0)
Requires-Dist: gradio (>=5.30.0,<6.0.0) ; extra == "ui" or extra == "full"
Requires-Dist: httpx (>=0.28.1,<0.29.0)
Requires-Dist: jinja2 (>=3.1.6,<4.0.0)
Requires-Dist: loguru (>=0.7.3,<0.8.0)
Requires-Dist: ollama (>=0.4.8,<0.5.0)
Requires-Dist: openai (>=1.75.0,<2.0.0)
Requires-Dist: pydantic (>=2.0,<3.0)
Requires-Dist: python-dotenv (>=1.1.0,<2.0.0)
Requires-Dist: python-frontmatter (>=1.1.0,<2.0.0)
Requires-Dist: requests (>=2.32.3,<3.0.0)
Project-URL: Homepage, https://memfuse.vercel.app
Project-URL: Repository, https://github.com/memfuse/memfuse-python
